simsapa/__init__.py
simsapa/__main__.py
simsapa/app/__init__.py
simsapa/app/db_models.py
simsapa/app/file_doc.py
simsapa/app/helpers.py
simsapa/app/types.py
simsapa/app/windows.py
simsapa/assets/__init__.py
simsapa/assets/icons/32x32/bx_search_alt_2.png
simsapa/assets/icons/32x32/bxs_book_bookmark.png
simsapa/assets/icons/32x32/bxs_book_content.png
simsapa/assets/icons/32x32/fa_redo.png
simsapa/assets/icons/32x32/fa_sync.png
simsapa/assets/icons/32x32/fa_times-circle.png
simsapa/assets/icons/gif/simsapa-loading.gif
simsapa/assets/icons/svg/bx_search_alt_2.svg
simsapa/assets/icons/svg/bxs_book_bookmark.svg
simsapa/assets/icons/svg/bxs_book_content.svg
simsapa/assets/icons/svg/fa_redo.svg
simsapa/assets/icons/svg/fa_sync.svg
simsapa/assets/icons/svg/fa_times-circle.svg
simsapa/assets/icons/svg_to_png.sh
simsapa/assets/icons.qrc
simsapa/assets/icons_rc.py
simsapa/assets/ui/__init__.py
simsapa/assets/ui/dictionaries_manager_window.ui
simsapa/assets/ui/dictionaries_manager_window_ui.py
simsapa/assets/ui/dictionary_search_window.ui
simsapa/assets/ui/dictionary_search_window_ui.py
simsapa/assets/ui/document_reader_window.ui
simsapa/assets/ui/document_reader_window_ui.py
simsapa/assets/ui/library_browser_window.ui
simsapa/assets/ui/library_browser_window_ui.py
simsapa/assets/ui/notes_browser_window.ui
simsapa/assets/ui/notes_browser_window_ui.py
simsapa/assets/ui/sutta_search_window.ui
simsapa/assets/ui/sutta_search_window_ui.py
simsapa/layouts/__init__.py
simsapa/layouts/dictionaries_manager.py
simsapa/layouts/dictionary_search.py
simsapa/layouts/document_reader.py
simsapa/layouts/download_appdata.py
simsapa/layouts/library_browser.py
simsapa/layouts/notes_browser.py
simsapa/layouts/sutta_search.py
simsapa/runner.py
simsapa-0.1.6.dist-info/LICENSE.txt
simsapa-0.1.6.dist-info/WHEEL
simsapa-0.1.6.dist-info/METADATA
simsapa-0.1.6.dist-info/RECORD
